cytobench/__init__.py
cytobench/coverage_estimator.py
cytobench/scoring_pipeline.py
cytobench-0.1.27.dist-info/LICENSE
cytobench-0.1.27.dist-info/METADATA
cytobench-0.1.27.dist-info/WHEEL
cytobench-0.1.27.dist-info/top_level.txt
cytobench-0.1.27.dist-info/RECORD
