Metadata-Version: 2.1
Name: cytobench
Version: 0.1.27
Summary: Benchmarking library for generative algorithms
Author-email: Nicolo' Lazzaro <nlazzaro@fbk.eu>
License: MIT License
Project-URL: Homepage, https://github.com/lazzaronico/cytobench
Keywords: benchmarking,generative algorithms,omics data
Classifier: Programming Language :: Python :: 3
Classifier: License :: OSI Approved :: MIT License
Classifier: Operating System :: OS Independent
License-File: LICENSE
Requires-Dist: numpy<2.0,>=1.25
Requires-Dist: scipy<2.0,>=1.11
Requires-Dist: scikit-learn<2.0,>=1.2
Requires-Dist: python-igraph>=0.11.6
Requires-Dist: leidenalg>=0.10.2
